[
  {
    "name": "GoWayFest 4.0",
    "url": "https://goway.io",
    "startDate": "2020-07-11",
    "endDate": "2020-07-11",
    "city": "Minsk",
    "country": "Belarus",
    "cfpUrl": "https://www.papercall.io/gowayfest4",
    "cfpEndDate": "2020-04-30",
    "twitter": "@GoWayFest"
  },
  {
    "name": "GopherCon Europe",
    "url": "https://gophercon.berlin",
    "startDate": "2020-07-30",
    "endDate": "2020-07-30",
    "city": "Berlin",
    "country": "Germany",
    "twitter": "@gopherconEU"
  }
]