[
  {
    "name": "RubyConf Au",
    "url": "https://rubyconf.org.au/2020",
    "startDate": "2020-02-20",
    "endDate": "2020-02-21",
    "city": "Melbourne",
    "country": "Australia",
    "twitter": "@rubyconf_au",
    "cfpUrl": "https://www.papercall.io/rubyconfau",
    "cfpEndDate": "2019-11-07"
  },
  {
    "name": "Euruko",
    "url": "https://euruko2020.org",
    "startDate": "2020-08-21",
    "endDate": "2020-08-22",
    "city": "Helsinki",
    "country": "Finland",
    "twitter": "@euruko"
  }
]