[
  {
    "name": "C++ Now",
    "url": "https://cppnow.org",
    "startDate": "2022-05-01",
    "endDate": "2022-05-06",
    "city": "Aspen, CO",
    "country": "U.S.A.",
    "online": false,
    "cocUrl": "https://cppnow.org/about/code_of_conduct",
    "twitter": "@cppnow"
  },
  {
    "name": "CppNorth",
    "url": "https://cppnorth.ca",
    "startDate": "2022-07-17",
    "endDate": "2022-07-20",
    "city": "Toronto",
    "country": "Canada",
    "online": false,
    "twitter": "@cppnorth"
  }
]