[
  {
    "name": "JSConf Budapest",
    "url": "https://jsconfbp.com",
    "startDate": "2022-06-02",
    "endDate": "2022-06-03",
    "city": "Budapest",
    "country": "Hungary",
    "online": false,
    "twitter": "@jsconfbp"
  },
  {
    "name": "HalfStack Newquay",
    "url": "https://halfstackconf.com/newquay/",
    "startDate": "2022-07-01",
    "endDate": "2022-07-01",
    "city": "Newquay",
    "country": "U.K.",
    "twitter": "@halfstackconf",
    "cocUrl": "https://halfstackconf.com/newquay/code-of-conduct/"
  },
  {
    "name": "Nordic.js",
    "url": "https://nordicjs.com",
    "startDate": "2022-10-06",
    "endDate": "2022-10-07",
    "city": "Stockholm",
    "country": "Sweden",
    "online": false,
    "twitter": "@nordicjs",
    "cocUrl": "https://nordicjs.com/code-of-conduct"
  },
  {
    "name": "VueJS Amsterdam",
    "startDate": "2022-02-10",
    "endDate": "2022-02-11",
    "city": "Amsterdam",
    "country": "Netherlands",
    "online": true,
    "twitter": "@vuejsamsterdam",
    "cocUrl": "https://vuejs.amsterdam/code-of-conduct",
    "url": "https://vuejs.amsterdam"
  }
]