[
  {
    "name": "FITC Amsterdam",
    "url": "http://fitc.ca/event/am19/",
    "startDate": "2019-02-18",
    "endDate": "2019-02-19",
    "city": "Amsterdam",
    "country": "Netherlands",
    "twitter": "@fitc"
  },
  {
    "name": "Women in Analytics Conference",
    "url": "https://www.womeninanalytics.org/",
    "startDate": "2019-03-21",
    "endDate": "2019-03-22",
    "city": "Columbus, OH",
    "country": "U.S.A.",
    "twitter": "@wia_conference",
    "cfpUrl": "https://www.womeninanalytics.org/call-for-speakers",
    "cfpEndDate": "2018-11-23"
  },
  {
    "name": "Reinforce AI Conference",
    "url": "https://reinforceconf.com",
    "startDate": "2019-03-21",
    "endDate": "2019-03-22",
    "city": "Budapest",
    "country": "Hungary",
    "cfpUrl": "https://www.papercall.io/reinforce-ai-2019",
    "cfpEndDate": "2018-11-30"
  },
  {
    "name": "Kafka Summit New York",
    "url": "https://kafka-summit.org/events/kafka-summit-new-york-2019",
    "startDate": "2019-04-02",
    "endDate": "2019-04-02",
    "city": "New York",
    "country": "U.S.A.",
    "twitter": "@ConfluentInc",
    "cfpUrl": "https://kafka-summit.org/kafka-summit-new-york-2019/speakers/",
    "cfpEndDate": "2018-12-20"
  },
  {
    "name": "FITC Toronto",
    "url": "http://fitc.ca/event/to19/",
    "startDate": "2019-04-21",
    "endDate": "2019-04-23",
    "city": "Toronto",
    "country": "Canada",
    "twitter": "@fitc"
  },
  {
    "name": "Kafka Summit London",
    "url": "https://kafka-summit.org/events/kafka-summit-london-2019",
    "startDate": "2019-05-13",
    "endDate": "2019-05-14",
    "city": "London",
    "country": "U.K.",
    "twitter": "@ConfluentInc",
    "cfpUrl": "https://kafka-summit.org/kafka-summit-london-2019/speakers/",
    "cfpEndDate": "2018-12-20"
  },
  {
    "name": "J on the Beach",
    "url": "https://jonthebeach.com/",
    "startDate": "2019-05-15",
    "endDate": "2019-05-17",
    "city": "Marbella",
    "country": "Spain",
    "twitter": "@jotb19",
    "cfpUrl": "https://www.papercall.io/jotb19",
    "cfpEndDate": "2019-02-04"
  }
]
