[
  {
    "name": "DataWorks Summit",
    "url": "https://dataworkssummit.com/melbourne-2019",
    "startDate": "2019-02-06",
    "endDate": "2019-02-06",
    "city": "Melbourne",
    "country": "Australia",
    "twitter": "@DataWorksSummit"
  },
  {
    "name": "FITC Amsterdam",
    "url": "http://fitc.ca/event/am19/",
    "startDate": "2019-02-18",
    "endDate": "2019-02-19",
    "city": "Amsterdam",
    "country": "Netherlands",
    "twitter": "@fitc"
  },
  {
    "name": "Applied AI",
    "url": "https://www.appliedai.co.uk",
    "startDate": "2019-03-01",
    "endDate": "2019-03-01",
    "city": "London",
    "country": "U.K.",
    "twitter": "@appliedaiconf"
  },
  {
    "name": "DataWorks Summit",
    "url": "https://dataworkssummit.com/barcelona-2019",
    "startDate": "2019-03-18",
    "endDate": "2019-03-21",
    "city": "Barcelona",
    "country": "Spain",
    "twitter": "@DataWorksSummit"
  },
  {
    "name": "Women in Analytics Conference",
    "url": "https://www.womeninanalytics.org/",
    "startDate": "2019-03-21",
    "endDate": "2019-03-22",
    "city": "Columbus, OH",
    "country": "U.S.A.",
    "twitter": "@wia_conference",
    "cfpUrl": "https://www.womeninanalytics.org/call-for-speakers",
    "cfpEndDate": "2018-11-23"
  },
  {
    "name": "Reinforce AI Conference",
    "url": "https://reinforceconf.com",
    "startDate": "2019-03-21",
    "endDate": "2019-03-22",
    "city": "Budapest",
    "country": "Hungary",
    "cfpUrl": "https://www.papercall.io/reinforce-ai-2019",
    "cfpEndDate": "2018-11-30"
  },
  {
    "name": "Kafka Summit New York",
    "url": "https://kafka-summit.org/events/kafka-summit-new-york-2019",
    "startDate": "2019-04-02",
    "endDate": "2019-04-02",
    "city": "New York",
    "country": "U.S.A.",
    "twitter": "@ConfluentInc",
    "cfpUrl": "https://kafka-summit.org/kafka-summit-new-york-2019/speakers/",
    "cfpEndDate": "2018-12-20"
  },
  {
    "name": "QCon.ai",
    "url": "http://bit.ly/2AZ7VHo",
    "startDate": "2019-04-15",
    "endDate": "2019-04-17",
    "city": "San Francisco",
    "country": "U.S.A.",
    "twitter": "@QConAI",
    "cfpUrl": "http://bit.ly/2AZ7VHo",
    "cfpEndDate": "2019-01-24"
  },
  {
    "name": "FITC Toronto",
    "url": "http://fitc.ca/event/to19/",
    "startDate": "2019-04-21",
    "endDate": "2019-04-23",
    "city": "Toronto",
    "country": "Canada",
    "twitter": "@fitc"
  },
  {
    "name": "GOTO",
    "url": "http://gotochgo.com",
    "startDate": "2019-04-28",
    "endDate": "2019-05-02",
    "city": "Chicago, IL",
    "country": "U.S.A.",
    "twitter": "@gotochgo"
  },
  {
    "name": "Kafka Summit London",
    "url": "https://kafka-summit.org/events/kafka-summit-london-2019",
    "startDate": "2019-05-13",
    "endDate": "2019-05-14",
    "city": "London",
    "country": "U.K.",
    "twitter": "@ConfluentInc",
    "cfpUrl": "https://kafka-summit.org/kafka-summit-london-2019/speakers/",
    "cfpEndDate": "2018-12-20"
  },
  {
    "name": "J on the Beach",
    "url": "https://jonthebeach.com/",
    "startDate": "2019-05-15",
    "endDate": "2019-05-17",
    "city": "Marbella",
    "country": "Spain",
    "twitter": "@jotb19",
    "cfpUrl": "https://www.papercall.io/jotb19",
    "cfpEndDate": "2019-02-04"
  },
  {
    "name": "DataWorks Summit",
    "url": "https://dataworkssummit.com/washington-dc-2019",
    "startDate": "2019-05-20",
    "endDate": "2019-05-23",
    "city": "Washington, DC",
    "country": "U.S.A.",
    "twitter": "@DataWorksSummit"
  },
  {
    "name": "Percona Live",
    "url": "https://www.percona.com/live",
    "startDate": "2019-05-28",
    "endDate": "2019-05-30",
    "city": "Austin, TX",
    "country": "U.S.A.",
    "twitter": "@percona",
    "cfpUrl": "https://perconacfp.hubb.me",
    "cfpEndDate": "2019-01-27"
  },
  {
    "name": "PGCon",
    "url": "https://www.pgcon.org/2019",
    "startDate": "2019-05-28",
    "endDate": "2019-05-31",
    "city": "Ottawa",
    "country": "Canada",
    "twitter": "@pgcon"
  },
  {
    "name": "GOTO",
    "url": "https://gotoams.nl",
    "startDate": "2019-06-17",
    "endDate": "2019-06-19",
    "city": "Amsterdam",
    "country": "Netherlands",
    "twitter": "@gotoamst"
  },
  {
    "name": "Infiniteconf",
    "url": "https://skillsmatter.com/conferences/11187-infiniteconf-2019-the-conference-on-big-data-and-ai#overview",
    "startDate": "2019-07-04",
    "endDate": "2019-07-05",
    "city": "London",
    "country": "U.K.",
    "twitter": "@skillsmatter",
    "cfpUrl": "https://skillsmatter.com/conferences/11187-infiniteconf-2019-the-conference-on-big-data-and-ai#get_involved",
    "cfpEndDate": "2019-02-28"
  },
  {
    "name": "AI Expo Africa",
    "url": "http://aiexpoafrica.com",
    "startDate": "2019-09-04",
    "endDate": "2020-09-05",
    "city": "Cape Town",
    "country": "South Africa",
    "twitter": "@aiexpoafrica"
  },
  {
    "name": "IEEE International Conference on Data Science and Advanced Analytics (DSAA)",
    "url": "http://www.dsaa.co",
    "startDate": "2019-10-05",
    "endDate": "2019-10-08",
    "city": "Washington, DC",
    "country": "U.S.A.",
    "twitter": "@IEEEDSAA"
  },
  {
    "name": "IEEE 29th International Workshop on Machine Learning for Signal Processing (MLSP)",
    "url": "https://conferences.ieee.org/conferences_events/conferences/conferencedetails/46386",
    "startDate": "2019-10-13",
    "endDate": "2019-10-16",
    "city": "Pittsburgh, PA",
    "country": "U.S.A."
  }
]