[
  {
    "name": "betterCode() GenAI",
    "url": "https://genai.bettercode.eu",
    "startDate": "2025-01-21",
    "endDate": "2025-01-21",
    "online": true,
    "locales": "DE",
    "cocUrl": "https://genai.bettercode.eu/code_of_conduct.php?source=0"
  },
  {
    "name": "IEEE/SICE SII",
    "url": "https://sice-si.org/SII2025/sii2025.html",
    "startDate": "2025-01-21",
    "endDate": "2025-01-24",
    "city": "Munich",
    "country": "Germany",
    "online": false,
    "locales": "EN"
  },
  {
    "name": "AI DevWorld",
    "url": "https://aidevworld.com",
    "startDate": "2025-02-11",
    "endDate": "2025-02-20",
    "city": "Santa Clara, CA",
    "country": "U.S.A.",
    "online": true,
    "locales": "EN",
    "twitter": "@AIDevWorld"
  },
  {
    "name": "CDAO UK",
    "url": "https://cdao-uk.coriniumintelligence.com",
    "startDate": "2025-02-12",
    "endDate": "2025-02-13",
    "city": "London",
    "country": "U.K.",
    "online": false,
    "locales": "EN",
    "twitter": "@CoriniumGlobal"
  },
  {
    "name": "PGConf India",
    "url": "https://pgconf.in/conferences/pgconfin2025",
    "startDate": "2025-03-05",
    "endDate": "2025-03-07",
    "city": "Bengaluru",
    "country": "India",
    "online": false,
    "locales": "EN",
    "cocUrl": "https://pgconf.in/pages/coc"
  },
  {
    "name": "Nordic PGDay",
    "url": "https://2025.nordicpgday.org/",
    "startDate": "2025-03-18",
    "endDate": "2025-03-18",
    "city": "Copenhagen",
    "country": "Denmark",
    "online": false,
    "locales": "EN",
    "cocUrl": "https://2025.nordicpgday.org/about/#coc"
  },
  {
    "name": "PGDay Paris",
    "url": "https://2025.pgday.paris/",
    "startDate": "2025-03-20",
    "endDate": "2025-03-20",
    "city": "Paris",
    "country": "France",
    "online": false,
    "locales": "EN"
  },
  {
    "name": "AI Integration & Autonomous Mobility",
    "url": "https://www.automantia.in/aiam24-munich",
    "startDate": "2025-04-03",
    "endDate": "2025-04-03",
    "city": "Munich",
    "country": "Germany",
    "online": false,
    "locales": "EN",
    "offersSignLanguageOrCC": true
  },
  {
    "name": "Data Science Next Conference",
    "url": "https://dscnextcon.com/",
    "startDate": "2025-05-07",
    "endDate": "2025-05-09",
    "city": "Amsterdam",
    "country": "Netherlands",
    "locales": "EN"
  },
  {
    "name": "ETHDam",
    "url": "https://www.ethdam.com",
    "startDate": "2025-05-09",
    "endDate": "2025-05-11",
    "city": "Amsterdam",
    "country": "Netherlands",
    "online": false,
    "locales": "EN",
    "cocUrl": "https://www.ethdam.com/general-5",
    "twitter": "@cryptocanal"
  },
  {
    "name": "AI & Machine Learning Summit",
    "url": "https://www.dbta.com/DataSummit/2025/AIMachineLearningSummit.aspx",
    "startDate": "2025-05-14",
    "endDate": "2025-05-15",
    "city": "Boston, MA",
    "country": "U.S.A.",
    "locales": "EN"
  },
  {
    "name": "Rise of AI",
    "url": "https://riseof.ai/conference-2025/",
    "startDate": "2025-05-14",
    "endDate": "2025-05-15",
    "city": "Berlin",
    "country": "Germany",
    "locales": "EN"
  },
  {
    "name": "Minds Mastering Machines - M3",
    "url": "https://www.m3-konferenz.de",
    "startDate": "2025-05-20",
    "endDate": "2025-05-21",
    "city": "Karlsruhe",
    "country": "Germany",
    "online": false,
    "locales": "DE",
    "cocUrl": "https://www.m3-konferenz.de/code_of_conduct.php?source=0",
    "cfpUrl": "https://www.m3-konferenz.de/cfp.php",
    "cfpEndDate": "2024-11-28"
  },
  {
    "name": "ICMLT",
    "url": "https://www.icmlt.org/",
    "startDate": "2025-05-23",
    "endDate": "2025-05-25",
    "city": "Helsinki",
    "country": "Finland",
    "locales": "EN"
  },
  {
    "name": "MLCon",
    "url": "https://mlconference.ai/munich",
    "startDate": "2025-05-23",
    "endDate": "2025-05-26",
    "city": "Munich",
    "country": "Germany",
    "online": true,
    "locales": "EN",
    "cocUrl": "https://mlconference.ai/code-of-conduct",
    "twitter": "@mlconference"
  },
  {
    "name": "IT-GRC-Kongress",
    "url": "https://www.grc-kongress.de",
    "startDate": "2025-05-26",
    "endDate": "2025-05-27",
    "city": "Cologne",
    "country": "Germany",
    "online": false,
    "locales": "DE",
    "cocUrl": "https://www.grc-kongress.de/code_of_conduct.php?source=0",
    "cfpUrl": "https://www.grc-kongress.de/cfp.php",
    "cfpEndDate": "2025-01-15"
  },
  {
    "name": "CONFidence",
    "url": "https://confidence-conference.org",
    "startDate": "2025-06-02",
    "endDate": "2025-06-03",
    "city": "Kraków",
    "country": "Poland",
    "online": false,
    "locales": "EN,PL",
    "cocUrl": "https://confidence-conference.org/code-of-conduct",
    "twitter": "@CONFidenceConf"
  },
  {
    "name": "EuroSTAR",
    "url": "https://conference.eurostarsoftwaretesting.com",
    "startDate": "2025-06-03",
    "endDate": "2025-06-06",
    "city": "Edinburgh",
    "country": "U.K.",
    "online": false,
    "locales": "EN",
    "cocUrl": "https://conference.eurostarsoftwaretesting.com/anti-harassment-policy",
    "twitter": "@esconfs"
  },
  {
    "name": "AI Con USA",
    "url": "https://aiconusa.techwell.com",
    "startDate": "2025-06-08",
    "endDate": "2025-06-13",
    "city": "Seattle, WA",
    "country": "U.S.A.",
    "online": true,
    "locales": "EN",
    "cfpUrl": "https://aiconusa.techwell.com/speak-ai-con-usa",
    "cfpEndDate": "2024-11-25",
    "twitter": "@techwell"
  }
]