[
  {
    "name": "Chaos Carnival",
    "url": "https://chaoscarnival.io",
    "startDate": "2025-01-22",
    "endDate": "2025-01-23",
    "online": true,
    "locales": "EN",
    "cocUrl": "https://2024.chaoscarnival.io/code-of-conduct",
    "cfpUrl": "https://www.papercall.io/chaoscarnival2025",
    "cfpEndDate": "2024-11-03",
    "twitter": "@chaoscarnivalio"
  },
  {
    "name": "Conf42 Chaos Engineering",
    "url": "https://www.conf42.com/ce2025",
    "startDate": "2025-02-13",
    "endDate": "2025-02-13",
    "online": true,
    "locales": "EN",
    "cocUrl": "https://www.conf42.com/code-of-conduct",
    "twitter": "@conf42com"
  },
  {
    "name": "SREDay",
    "url": "https://sreday.com/2025-san-francisco-q2",
    "startDate": "2025-04-11",
    "endDate": "2025-04-11",
    "city": "San Francisco, CA",
    "country": "U.S.A.",
    "online": false,
    "locales": "EN",
    "twitter": "@sreday_com"
  },
  {
    "name": "SREDay",
    "url": "https://sreday.com/2025-redmond-q2",
    "startDate": "2025-04-14",
    "endDate": "2025-04-14",
    "city": "Redmond, WA",
    "country": "U.S.A.",
    "online": false,
    "locales": "EN",
    "twitter": "@sreday_com"
  },
  {
    "name": "PlatforMa",
    "url": "https://platfor-ma.com",
    "startDate": "2025-05-20",
    "endDate": "2025-05-20",
    "city": "Tel Aviv",
    "country": "Israel",
    "online": false,
    "locales": "EN,HE",
    "cocUrl": "https://www.platfor-ma.com/code-of-conduct",
    "cfpUrl": "https://sessionize.com/platforma2025",
    "cfpEndDate": "2025-02-02"
  },
  {
    "name": "SREDay - Cologne",
    "url": "https://sreday.com/2025-cologne-q2",
    "startDate": "2025-06-12",
    "endDate": "2025-06-12",
    "city": "Cologne",
    "country": "Germany",
    "online": false,
    "locales": "EN",
    "twitter": "@sreday_com"
  },
  {
    "name": "TechSummit Amsterdam",
    "url": "https://techsummit.io",
    "startDate": "2025-09-16",
    "endDate": "2025-09-16",
    "city": "Amsterdam",
    "country": "Netherlands",
    "online": false,
    "locales": "EN",
    "cfpUrl": "https://techsummit.io/call-for-papers",
    "cfpEndDate": "2025-05-01"
  }
]